impt/__init__.py
impt/__version__.py
impt/base.py
impt/perturb.py
impt/fpfs/__init__.py
impt/fpfs/default.py
impt/fpfs/future.py
impt/fpfs/linobs.py
impt/fpfs/nlobs.py
impt/fpfs/test_utils.py
impt/fpfs/utils.py
impt/fpfs4/__init__.py
impt/fpfs4/default.py
impt/fpfs4/linobs.py
impt/fpfs4/nlobs.py
impt/fpfs4/test_utils.py
impt/fpfs4/utils.py
impt-0.1.2.data/scripts/impt_config
impt-0.1.2.data/scripts/impt_make_plots.py
impt-0.1.2.data/scripts/impt_std_future.py
impt-0.1.2.data/scripts/impt_std_future_from_image.py
impt-0.1.2.data/scripts/impt_std_future_snr.py
impt-0.1.2.data/scripts/impt_summary_desc_future.py
impt-0.1.2.data/scripts/impt_summary_hsc.py
impt-0.1.2.dist-info/LICENSE
impt-0.1.2.dist-info/METADATA
impt-0.1.2.dist-info/WHEEL
impt-0.1.2.dist-info/top_level.txt
impt-0.1.2.dist-info/RECORD
