Metadata-Version: 2.1
Name: impt
Version: 0.1.2
Summary: Auto-diff Estimator of Lensing Perturbations
Home-page: https://github.com/mr-superonion/imPT/
Author: Xiangchong Li
Author-email: mr.superonion@hotmail.com
Requires-Python: >=3.8
License-File: LICENSE
Requires-Dist: numpy
Requires-Dist: schwimmbad
Requires-Dist: jax >=0.4.9
Requires-Dist: jaxlib >=0.4.9
Requires-Dist: flax
Requires-Dist: fitsio
